self_healing_driver/__init__.py
self_healing_driver/element_info.py
self_healing_driver/self_healing_driver.py
self_healing_driver/train.py
self_healing_driver/web_element_info.py
self_healing_driver-0.2.dist-info/METADATA
self_healing_driver-0.2.dist-info/WHEEL
self_healing_driver-0.2.dist-info/top_level.txt
self_healing_driver-0.2.dist-info/RECORD
