Metadata-Version: 2.1
Name: self_healing_driver
Version: 0.2
Requires-Dist: beautifulsoup4
Requires-Dist: docx
Requires-Dist: docx2python
Requires-Dist: docx2txt
Requires-Dist: faiss-cpu
Requires-Dist: joblib
Requires-Dist: jsonpatch
Requires-Dist: jsonpath-python
Requires-Dist: jsonpointer
Requires-Dist: jsonschema
Requires-Dist: jsonschema-specifications
Requires-Dist: keras
Requires-Dist: langchain
Requires-Dist: langchain-community
Requires-Dist: langchain-core
Requires-Dist: langchain-experimental
Requires-Dist: langchain-google-genai
Requires-Dist: langchain-openai
Requires-Dist: langchain-text-splitters
Requires-Dist: langcodes
Requires-Dist: langdetect
Requires-Dist: langsmith
Requires-Dist: lazy-loader
Requires-Dist: libclang
Requires-Dist: lxml
Requires-Dist: matplotlib
Requires-Dist: mysql-connector
Requires-Dist: mysql-connector-python
Requires-Dist: nltk
Requires-Dist: numpy
Requires-Dist: openai
Requires-Dist: opencv-python
Requires-Dist: packaging
Requires-Dist: pandas
Requires-Dist: pillow
Requires-Dist: pinecone
Requires-Dist: pinecone-client
Requires-Dist: pinecone-plugin-interface
Requires-Dist: pyparsing
Requires-Dist: pypdf
Requires-Dist: pypdf2
Requires-Dist: python-dateutil
Requires-Dist: python-docx
Requires-Dist: python-dotenv
Requires-Dist: requests
Requires-Dist: scikit-image
Requires-Dist: scikit-learn
Requires-Dist: scipy
Requires-Dist: selenium
Requires-Dist: sentencepiece
Requires-Dist: setuptools
Requires-Dist: tensorflow
Requires-Dist: tensorflow-hub
Requires-Dist: tensorflow-intel
Requires-Dist: textstat
Requires-Dist: tf-keras
Requires-Dist: tiktoken
Requires-Dist: tokenizers
Requires-Dist: torch
Requires-Dist: tqdm
Requires-Dist: transformers
Requires-Dist: typing-inspect
Requires-Dist: urllib3
